<casebody xmlns="http://nrs.harvard.edu/urn-3:HLS.Libr.US_Case_Law.Schema.Case_Body:v1" firstpage="673" lastpage="673">\n
	<parties id="b705-6">Myrtle E. Brown, appellee, v. American Benefit Life Insurance Company, formerly Merchants &amp; Bankers Life Insurance Company, appellant.</parties>\n
	<decisiondate id="Acm8">Opinion filed March 2, 1928.</decisiondate>\n
	<attorneys id="b705-8">Gillespie, Burke &amp; Gillespie, for appellant; Parker &amp; Bauer, Louis P. Gillespie and Hugh J. Dobbs, of counsel. G. P. Denton and Paul Taylor, for appellee.</attorneys>\n
	<opinion type="majority">\n
		<author id="b705-9">Mr. Justice Wolfe</author>\n
		<p id="AD1Z">delivered the opinion of the court.</p>\n
	</opinion>\n
</casebody>\n
